setup.py
invoice_creator.egg-info/PKG-INFO
invoice_creator.egg-info/SOURCES.txt
invoice_creator.egg-info/dependency_links.txt
invoice_creator.egg-info/requires.txt
invoice_creator.egg-info/top_level.txt
invoicing/__init__.py
invoicing/invoice.py